mcp_power_calculator/__init__.py
mcp_power_calculator-0.1.0.dist-info/METADATA
mcp_power_calculator-0.1.0.dist-info/WHEEL
mcp_power_calculator-0.1.0.dist-info/licenses/LICENSE
mcp_power_calculator-0.1.0.dist-info/RECORD
