Metadata-Version: 2.4
Name: mcp-power-calculator
Version: 0.1.0
Summary: A simple MCP application for power calculation
Project-URL: Homepage, https://github.com/yourusername/mcp-power-calculator
Project-URL: Bug Tracker, https://github.com/yourusername/mcp-power-calculator/issues
Author-email: Your Name <your.email@example.com>
License-File: LICENSE
Classifier: License :: OSI Approved :: MIT License
Classifier: Operating System :: OS Independent
Classifier: Programming Language :: Python :: 3
Requires-Python: >=3.7
Requires-Dist: mcp>=0.1.0
Requires-Dist: requests>=2.31.0
